alumathgroup3/__init__.py
alumathgroup3/matrix.py
alumathgroup3-1.0.0.dist-info/licenses/LICENCE
alumathgroup3-1.0.0.dist-info/METADATA
alumathgroup3-1.0.0.dist-info/WHEEL
alumathgroup3-1.0.0.dist-info/top_level.txt
alumathgroup3-1.0.0.dist-info/RECORD
