Metadata-Version: 2.4
Name: alumathgroup3
Version: 1.0.0
Summary: A simple Python library for matrix multiplication
Home-page: https://github.com/InshutiSouvede/Formative-2-Peer-Group-3
Author: Group 3
Author-email: Erneste Ntezirizaza <erneste.ntezirizaza@gmail.com>
License: MIT
Classifier: Development Status :: 4 - Beta
Classifier: Intended Audience :: Developers
Classifier: License :: OSI Approved :: MIT License
Classifier: Operating System :: OS Independent
Classifier: Programming Language :: Python :: 3
Requires-Python: >=3.6
License-File: LICENCE
Dynamic: author
Dynamic: home-page
Dynamic: license-file
Dynamic: requires-python
